rfid.py
Chinese_RFID_Access_Control_Library-0.1.2.dist-info/LICENSE
Chinese_RFID_Access_Control_Library-0.1.2.dist-info/METADATA
Chinese_RFID_Access_Control_Library-0.1.2.dist-info/WHEEL
Chinese_RFID_Access_Control_Library-0.1.2.dist-info/top_level.txt
Chinese_RFID_Access_Control_Library-0.1.2.dist-info/RECORD
