Metadata-Version: 2.1
Name: Chinese-RFID-Access-Control-Library
Version: 0.1.2
Summary: A library for interfacing with one of the most common RFID Access Control System sold in China.
Home-page: https://github.com/pawl/Chinese-RFID-Access-Control-Library
Author: Paul Brown
Author-email: paul90brown@gmail.com
License: MIT
Download-URL: https://pypi.python.org/pypi/Chinese-RFID-Access-Control-Library
Keywords: rfid,access control
Platform: UNKNOWN
Classifier: License :: OSI Approved :: MIT License
Classifier: Programming Language :: Python :: 2
Classifier: Programming Language :: Python :: 3
